click_default_group.py
click_default_group-1.2.3.dist-info/LICENSE
click_default_group-1.2.3.dist-info/WHEEL
click_default_group-1.2.3.dist-info/METADATA
click_default_group-1.2.3.dist-info/RECORD
